Metadata-Version: 1.1
Name: PythonDatabaseModule
Version: 1.5.8
Summary: A database for python.It is offline and it is still in testing phase!
Home-page: UNKNOWN
Author: Jonian Bicaku
Author-email: joni.bicaku@gmail.com
License: MIT
Keywords: database
Platform: UNKNOWN
Classifier: Development Status :: 5 - Production/Stable
Classifier: Intended Audience :: Education
Classifier: Operating System :: Unix
Classifier: Operating System :: MacOS :: MacOS X
Classifier: Operating System :: Microsoft :: Windows
Classifier: License :: OSI Approved :: MIT License
Classifier: Programming Language :: Python :: 3
